py3streams/__init__.py
py3streams/dict_stream.py
py3streams/int_stream.py
py3streams/optional.py
py3streams/stream.py
py3streams/stream_base.py
py3streams-0.1.6.dist-info/LICENSE
py3streams-0.1.6.dist-info/METADATA
py3streams-0.1.6.dist-info/WHEEL
py3streams-0.1.6.dist-info/top_level.txt
py3streams-0.1.6.dist-info/RECORD
