Metadata-Version: 2.1
Name: py3streams
Version: 0.1.6
Summary: Package for manipulate collections with streams and generators.
Home-page: UNKNOWN
Author: Marek Adam Gancarz
Author-email: 
License: UNKNOWN
Keywords: python,python3,stream,list,tuple,set,dict,collection
Platform: UNKNOWN
Classifier: Programming Language :: Python :: 3
Classifier: Operating System :: Unix
License-File: LICENSE
